AnaviInfraredPhat/__init__.py
AnaviInfraredPhat/__main__.py
AnaviInfraredPhat/version.py
AnaviInfraredPhat-0.0.11.dist-info/LICENSE
AnaviInfraredPhat-0.0.11.dist-info/METADATA
AnaviInfraredPhat-0.0.11.dist-info/WHEEL
AnaviInfraredPhat-0.0.11.dist-info/top_level.txt
AnaviInfraredPhat-0.0.11.dist-info/RECORD
