Metadata-Version: 2.1
Name: AnaviInfraredPhat
Version: 0.0.11
Summary: AnaviInfraredPhat
Home-page: https://github.com/KurisuD/AnaviInfraredPhat
Author: KurisuD
Author-email: KurisuD@pypi.darnand.net
Classifier: Programming Language :: Python :: 3 :: Only
Classifier: Programming Language :: Python :: 3.5
Classifier: License :: Public Domain
Classifier: Operating System :: POSIX :: Linux
Classifier: Topic :: Home Automation
License-File: LICENSE
Requires-Dist: pigpio
Requires-Dist: pyzmq
Requires-Dist: pap-logger
